AUTHORS.md
CHANGELOG.md
MANIFEST.in
README.md
dev-requirements.in
dev-requirements.txt
requirements.in
requirements.txt
setup.cfg
setup.py
pays/__init__.py
pays.egg-info/PKG-INFO
pays.egg-info/SOURCES.txt
pays.egg-info/dependency_links.txt
pays.egg-info/top_level.txt
pays/data/cym.json
pays/data/deu.json
pays/data/eng.json
pays/data/est.json
pays/data/fin.json
pays/data/fra.json
pays/data/hrv.json
pays/data/ita.json
pays/data/jpn.json
pays/data/nld.json
pays/data/por.json
pays/data/rus.json
pays/data/slk.json
pays/data/spa.json
pays/data/zho.json