Metadata-Version: 1.1
Name: pays
Version: 0.2.3
Summary: Liste de pays en dict
Home-page: https://gitlab.com/canarduck/pays
Author: Canarduck
Author-email: renaud@canarduck.com
License: UNKNOWN
Keywords: countries iso3166
Platform: UNKNOWN
Classifier: Programming Language :: Python :: 3
Classifier: Intended Audience :: Developers
Classifier: Development Status :: 3 - Alpha
Classifier: License :: OSI Approved :: MIT License
Classifier: Operating System :: OS Independent
